[
    {
        "file_path": "mnist_784.csv",
        "chunk_size": 70000,
        "views": "{'bottom_right', 'top_right', 'original', 'tda', 'top_left', 'bottom_left'}",
        "num_jobs": 28,
        "save_sample_views": false,
        "vary_train_split": false,
        "subsample_dataset": false,
        "exp_name": "exp_icecream_noise_saltpepper_30",
        "random_state": 433345055,
        "train_split": 0.8,
        "test_split": 0.3,
        "noise_enabled": true,
        "noise_type": "salt_pepper",
        "noise_quantity": 0.3,
        "noise_transparency": 0,
        "results_dir": "results/exp_icecream_noise_saltpepper_30",
        "log_dir": "logs/exp_icecream_noise_saltpepper_30"
    },
    {
        "file_path": "mnist_784.csv",
        "chunk_size": 70000,
        "views": "{'bottom_right', 'top_right', 'original', 'tda', 'top_left', 'bottom_left'}",
        "num_jobs": 28,
        "save_sample_views": false,
        "vary_train_split": false,
        "subsample_dataset": false,
        "exp_name": "exp_icecream_noise_saltpepper_30",
        "random_state": 386563478,
        "train_split": 0.8,
        "test_split": 0.3,
        "noise_enabled": true,
        "noise_type": "salt_pepper",
        "noise_quantity": 0.3,
        "noise_transparency": 0,
        "results_dir": "results/exp_icecream_noise_saltpepper_30",
        "log_dir": "logs/exp_icecream_noise_saltpepper_30"
    },
    {
        "file_path": "mnist_784.csv",
        "chunk_size": 70000,
        "views": "{'bottom_right', 'top_right', 'original', 'tda', 'top_left', 'bottom_left'}",
        "num_jobs": 28,
        "save_sample_views": false,
        "vary_train_split": false,
        "subsample_dataset": false,
        "exp_name": "exp_icecream_noise_saltpepper_30",
        "random_state": 396058858,
        "train_split": 0.8,
        "test_split": 0.3,
        "noise_enabled": true,
        "noise_type": "salt_pepper",
        "noise_quantity": 0.3,
        "noise_transparency": 0,
        "results_dir": "results/exp_icecream_noise_saltpepper_30",
        "log_dir": "logs/exp_icecream_noise_saltpepper_30"
    },
    {
        "file_path": "mnist_784.csv",
        "chunk_size": 70000,
        "views": "{'bottom_right', 'top_right', 'original', 'tda', 'top_left', 'bottom_left'}",
        "num_jobs": 28,
        "save_sample_views": false,
        "vary_train_split": false,
        "subsample_dataset": false,
        "exp_name": "exp_icecream_noise_saltpepper_30",
        "random_state": 874967727,
        "train_split": 0.8,
        "test_split": 0.3,
        "noise_enabled": true,
        "noise_type": "salt_pepper",
        "noise_quantity": 0.3,
        "noise_transparency": 0,
        "results_dir": "results/exp_icecream_noise_saltpepper_30",
        "log_dir": "logs/exp_icecream_noise_saltpepper_30"
    },
    {
        "file_path": "mnist_784.csv",
        "chunk_size": 70000,
        "views": "{'bottom_right', 'top_right', 'original', 'tda', 'top_left', 'bottom_left'}",
        "num_jobs": 28,
        "save_sample_views": false,
        "vary_train_split": false,
        "subsample_dataset": false,
        "exp_name": "exp_icecream_noise_saltpepper_30",
        "random_state": 551285262,
        "train_split": 0.8,
        "test_split": 0.3,
        "noise_enabled": true,
        "noise_type": "salt_pepper",
        "noise_quantity": 0.3,
        "noise_transparency": 0,
        "results_dir": "results/exp_icecream_noise_saltpepper_30",
        "log_dir": "logs/exp_icecream_noise_saltpepper_30"
    },
    {
        "file_path": "mnist_784.csv",
        "chunk_size": 70000,
        "views": "{'bottom_right', 'top_right', 'original', 'tda', 'top_left', 'bottom_left'}",
        "num_jobs": 28,
        "save_sample_views": false,
        "vary_train_split": false,
        "subsample_dataset": false,
        "exp_name": "exp_icecream_noise_saltpepper_30",
        "random_state": 31293048,
        "train_split": 0.8,
        "test_split": 0.3,
        "noise_enabled": true,
        "noise_type": "salt_pepper",
        "noise_quantity": 0.3,
        "noise_transparency": 0,
        "results_dir": "results/exp_icecream_noise_saltpepper_30",
        "log_dir": "logs/exp_icecream_noise_saltpepper_30"
    },
    {
        "file_path": "mnist_784.csv",
        "chunk_size": 70000,
        "views": "{'bottom_right', 'top_right', 'original', 'tda', 'top_left', 'bottom_left'}",
        "num_jobs": 28,
        "save_sample_views": false,
        "vary_train_split": false,
        "subsample_dataset": false,
        "exp_name": "exp_icecream_noise_saltpepper_30",
        "random_state": 414321304,
        "train_split": 0.8,
        "test_split": 0.3,
        "noise_enabled": true,
        "noise_type": "salt_pepper",
        "noise_quantity": 0.3,
        "noise_transparency": 0,
        "results_dir": "results/exp_icecream_noise_saltpepper_30",
        "log_dir": "logs/exp_icecream_noise_saltpepper_30"
    },
    {
        "file_path": "mnist_784.csv",
        "chunk_size": 70000,
        "views": "{'bottom_right', 'top_right', 'original', 'tda', 'top_left', 'bottom_left'}",
        "num_jobs": 28,
        "save_sample_views": false,
        "vary_train_split": false,
        "subsample_dataset": false,
        "exp_name": "exp_icecream_noise_saltpepper_30",
        "random_state": 641177803,
        "train_split": 0.8,
        "test_split": 0.3,
        "noise_enabled": true,
        "noise_type": "salt_pepper",
        "noise_quantity": 0.3,
        "noise_transparency": 0,
        "results_dir": "results/exp_icecream_noise_saltpepper_30",
        "log_dir": "logs/exp_icecream_noise_saltpepper_30"
    },
    {
        "file_path": "mnist_784.csv",
        "chunk_size": 70000,
        "views": "{'bottom_right', 'top_right', 'original', 'tda', 'top_left', 'bottom_left'}",
        "num_jobs": 28,
        "save_sample_views": false,
        "vary_train_split": false,
        "subsample_dataset": false,
        "exp_name": "exp_icecream_noise_saltpepper_30",
        "random_state": 866933024,
        "train_split": 0.8,
        "test_split": 0.3,
        "noise_enabled": true,
        "noise_type": "salt_pepper",
        "noise_quantity": 0.3,
        "noise_transparency": 0,
        "results_dir": "results/exp_icecream_noise_saltpepper_30",
        "log_dir": "logs/exp_icecream_noise_saltpepper_30"
    },
    {
        "file_path": "mnist_784.csv",
        "chunk_size": 70000,
        "views": "{'bottom_right', 'top_right', 'original', 'tda', 'top_left', 'bottom_left'}",
        "num_jobs": 28,
        "save_sample_views": false,
        "vary_train_split": false,
        "subsample_dataset": false,
        "exp_name": "exp_icecream_noise_saltpepper_30",
        "random_state": 323175171,
        "train_split": 0.8,
        "test_split": 0.3,
        "noise_enabled": true,
        "noise_type": "salt_pepper",
        "noise_quantity": 0.3,
        "noise_transparency": 0,
        "results_dir": "results/exp_icecream_noise_saltpepper_30",
        "log_dir": "logs/exp_icecream_noise_saltpepper_30"
    },
    {
        "file_path": "mnist_784.csv",
        "chunk_size": 70000,
        "views": "{'bottom_right', 'top_right', 'original', 'tda', 'top_left', 'bottom_left'}",
        "num_jobs": 28,
        "save_sample_views": false,
        "vary_train_split": false,
        "subsample_dataset": false,
        "exp_name": "exp_icecream_noise_saltpepper_30",
        "random_state": 495435084,
        "train_split": 0.8,
        "test_split": 0.3,
        "noise_enabled": true,
        "noise_type": "salt_pepper",
        "noise_quantity": 0.3,
        "noise_transparency": 0,
        "results_dir": "results/exp_icecream_noise_saltpepper_30",
        "log_dir": "logs/exp_icecream_noise_saltpepper_30"
    },
    {
        "file_path": "mnist_784.csv",
        "chunk_size": 70000,
        "views": "{'bottom_right', 'top_right', 'original', 'tda', 'top_left', 'bottom_left'}",
        "num_jobs": 28,
        "save_sample_views": false,
        "vary_train_split": false,
        "subsample_dataset": false,
        "exp_name": "exp_icecream_noise_saltpepper_30",
        "random_state": 492643975,
        "train_split": 0.8,
        "test_split": 0.3,
        "noise_enabled": true,
        "noise_type": "salt_pepper",
        "noise_quantity": 0.3,
        "noise_transparency": 0,
        "results_dir": "results/exp_icecream_noise_saltpepper_30",
        "log_dir": "logs/exp_icecream_noise_saltpepper_30"
    },
    {
        "file_path": "mnist_784.csv",
        "chunk_size": 70000,
        "views": "{'bottom_right', 'top_right', 'original', 'tda', 'top_left', 'bottom_left'}",
        "num_jobs": 28,
        "save_sample_views": false,
        "vary_train_split": false,
        "subsample_dataset": false,
        "exp_name": "exp_icecream_noise_saltpepper_30",
        "random_state": 934066164,
        "train_split": 0.8,
        "test_split": 0.3,
        "noise_enabled": true,
        "noise_type": "salt_pepper",
        "noise_quantity": 0.3,
        "noise_transparency": 0,
        "results_dir": "results/exp_icecream_noise_saltpepper_30",
        "log_dir": "logs/exp_icecream_noise_saltpepper_30"
    },
    {
        "file_path": "mnist_784.csv",
        "chunk_size": 70000,
        "views": "{'bottom_right', 'top_right', 'original', 'tda', 'top_left', 'bottom_left'}",
        "num_jobs": 28,
        "save_sample_views": false,
        "vary_train_split": false,
        "subsample_dataset": false,
        "exp_name": "exp_icecream_noise_saltpepper_30",
        "random_state": 997573152,
        "train_split": 0.8,
        "test_split": 0.3,
        "noise_enabled": true,
        "noise_type": "salt_pepper",
        "noise_quantity": 0.3,
        "noise_transparency": 0,
        "results_dir": "results/exp_icecream_noise_saltpepper_30",
        "log_dir": "logs/exp_icecream_noise_saltpepper_30"
    },
    {
        "file_path": "mnist_784.csv",
        "chunk_size": 70000,
        "views": "{'bottom_right', 'top_right', 'original', 'tda', 'top_left', 'bottom_left'}",
        "num_jobs": 28,
        "save_sample_views": false,
        "vary_train_split": false,
        "subsample_dataset": false,
        "exp_name": "exp_icecream_noise_saltpepper_30",
        "random_state": 673869249,
        "train_split": 0.8,
        "test_split": 0.3,
        "noise_enabled": true,
        "noise_type": "salt_pepper",
        "noise_quantity": 0.3,
        "noise_transparency": 0,
        "results_dir": "results/exp_icecream_noise_saltpepper_30",
        "log_dir": "logs/exp_icecream_noise_saltpepper_30"
    },
    {
        "file_path": "mnist_784.csv",
        "chunk_size": 70000,
        "views": "{'bottom_right', 'top_right', 'original', 'tda', 'top_left', 'bottom_left'}",
        "num_jobs": 28,
        "save_sample_views": false,
        "vary_train_split": false,
        "subsample_dataset": false,
        "exp_name": "exp_icecream_noise_saltpepper_30",
        "random_state": 225729987,
        "train_split": 0.8,
        "test_split": 0.3,
        "noise_enabled": true,
        "noise_type": "salt_pepper",
        "noise_quantity": 0.3,
        "noise_transparency": 0,
        "results_dir": "results/exp_icecream_noise_saltpepper_30",
        "log_dir": "logs/exp_icecream_noise_saltpepper_30"
    },
    {
        "file_path": "mnist_784.csv",
        "chunk_size": 70000,
        "views": "{'bottom_right', 'top_right', 'original', 'tda', 'top_left', 'bottom_left'}",
        "num_jobs": 28,
        "save_sample_views": false,
        "vary_train_split": false,
        "subsample_dataset": false,
        "exp_name": "exp_icecream_noise_saltpepper_30",
        "random_state": 493864865,
        "train_split": 0.8,
        "test_split": 0.3,
        "noise_enabled": true,
        "noise_type": "salt_pepper",
        "noise_quantity": 0.3,
        "noise_transparency": 0,
        "results_dir": "results/exp_icecream_noise_saltpepper_30",
        "log_dir": "logs/exp_icecream_noise_saltpepper_30"
    },
    {
        "file_path": "mnist_784.csv",
        "chunk_size": 70000,
        "views": "{'bottom_right', 'top_right', 'original', 'tda', 'top_left', 'bottom_left'}",
        "num_jobs": 28,
        "save_sample_views": false,
        "vary_train_split": false,
        "subsample_dataset": false,
        "exp_name": "exp_icecream_noise_saltpepper_30",
        "random_state": 72461044,
        "train_split": 0.8,
        "test_split": 0.3,
        "noise_enabled": true,
        "noise_type": "salt_pepper",
        "noise_quantity": 0.3,
        "noise_transparency": 0,
        "results_dir": "results/exp_icecream_noise_saltpepper_30",
        "log_dir": "logs/exp_icecream_noise_saltpepper_30"
    },
    {
        "file_path": "mnist_784.csv",
        "chunk_size": 70000,
        "views": "{'bottom_right', 'top_right', 'original', 'tda', 'top_left', 'bottom_left'}",
        "num_jobs": 28,
        "save_sample_views": false,
        "vary_train_split": false,
        "subsample_dataset": false,
        "exp_name": "exp_icecream_noise_saltpepper_30",
        "random_state": 852846005,
        "train_split": 0.8,
        "test_split": 0.3,
        "noise_enabled": true,
        "noise_type": "salt_pepper",
        "noise_quantity": 0.3,
        "noise_transparency": 0,
        "results_dir": "results/exp_icecream_noise_saltpepper_30",
        "log_dir": "logs/exp_icecream_noise_saltpepper_30"
    },
    {
        "file_path": "mnist_784.csv",
        "chunk_size": 70000,
        "views": "{'bottom_right', 'top_right', 'original', 'tda', 'top_left', 'bottom_left'}",
        "num_jobs": 28,
        "save_sample_views": false,
        "vary_train_split": false,
        "subsample_dataset": false,
        "exp_name": "exp_icecream_noise_saltpepper_30",
        "random_state": 958762328,
        "train_split": 0.8,
        "test_split": 0.3,
        "noise_enabled": true,
        "noise_type": "salt_pepper",
        "noise_quantity": 0.3,
        "noise_transparency": 0,
        "results_dir": "results/exp_icecream_noise_saltpepper_30",
        "log_dir": "logs/exp_icecream_noise_saltpepper_30"
    },
    {
        "file_path": "mnist_784.csv",
        "chunk_size": 70000,
        "views": "{'bottom_right', 'top_right', 'original', 'tda', 'top_left', 'bottom_left'}",
        "num_jobs": 28,
        "save_sample_views": false,
        "vary_train_split": false,
        "subsample_dataset": false,
        "exp_name": "exp_icecream_noise_saltpepper_30",
        "random_state": 252939082,
        "train_split": 0.8,
        "test_split": 0.3,
        "noise_enabled": true,
        "noise_type": "salt_pepper",
        "noise_quantity": 0.3,
        "noise_transparency": 0,
        "results_dir": "results/exp_icecream_noise_saltpepper_30",
        "log_dir": "logs/exp_icecream_noise_saltpepper_30"
    },
    {
        "file_path": "mnist_784.csv",
        "chunk_size": 70000,
        "views": "{'bottom_right', 'top_right', 'original', 'tda', 'top_left', 'bottom_left'}",
        "num_jobs": 28,
        "save_sample_views": false,
        "vary_train_split": false,
        "subsample_dataset": false,
        "exp_name": "exp_icecream_noise_saltpepper_30",
        "random_state": 657377475,
        "train_split": 0.8,
        "test_split": 0.3,
        "noise_enabled": true,
        "noise_type": "salt_pepper",
        "noise_quantity": 0.3,
        "noise_transparency": 0,
        "results_dir": "results/exp_icecream_noise_saltpepper_30",
        "log_dir": "logs/exp_icecream_noise_saltpepper_30"
    },
    {
        "file_path": "mnist_784.csv",
        "chunk_size": 70000,
        "views": "{'bottom_right', 'top_right', 'original', 'tda', 'top_left', 'bottom_left'}",
        "num_jobs": 28,
        "save_sample_views": false,
        "vary_train_split": false,
        "subsample_dataset": false,
        "exp_name": "exp_icecream_noise_saltpepper_30",
        "random_state": 321423711,
        "train_split": 0.8,
        "test_split": 0.3,
        "noise_enabled": true,
        "noise_type": "salt_pepper",
        "noise_quantity": 0.3,
        "noise_transparency": 0,
        "results_dir": "results/exp_icecream_noise_saltpepper_30",
        "log_dir": "logs/exp_icecream_noise_saltpepper_30"
    },
    {
        "file_path": "mnist_784.csv",
        "chunk_size": 70000,
        "views": "{'bottom_right', 'top_right', 'original', 'tda', 'top_left', 'bottom_left'}",
        "num_jobs": 28,
        "save_sample_views": false,
        "vary_train_split": false,
        "subsample_dataset": false,
        "exp_name": "exp_icecream_noise_saltpepper_30",
        "random_state": 241006125,
        "train_split": 0.8,
        "test_split": 0.3,
        "noise_enabled": true,
        "noise_type": "salt_pepper",
        "noise_quantity": 0.3,
        "noise_transparency": 0,
        "results_dir": "results/exp_icecream_noise_saltpepper_30",
        "log_dir": "logs/exp_icecream_noise_saltpepper_30"
    },
    {
        "file_path": "mnist_784.csv",
        "chunk_size": 70000,
        "views": "{'bottom_right', 'top_right', 'original', 'tda', 'top_left', 'bottom_left'}",
        "num_jobs": 28,
        "save_sample_views": false,
        "vary_train_split": false,
        "subsample_dataset": false,
        "exp_name": "exp_icecream_noise_saltpepper_30",
        "random_state": 585573799,
        "train_split": 0.8,
        "test_split": 0.3,
        "noise_enabled": true,
        "noise_type": "salt_pepper",
        "noise_quantity": 0.3,
        "noise_transparency": 0,
        "results_dir": "results/exp_icecream_noise_saltpepper_30",
        "log_dir": "logs/exp_icecream_noise_saltpepper_30"
    },
    {
        "file_path": "mnist_784.csv",
        "chunk_size": 70000,
        "views": "{'bottom_right', 'top_right', 'original', 'tda', 'top_left', 'bottom_left'}",
        "num_jobs": 28,
        "save_sample_views": false,
        "vary_train_split": false,
        "subsample_dataset": false,
        "exp_name": "exp_icecream_noise_saltpepper_30",
        "random_state": 584265474,
        "train_split": 0.8,
        "test_split": 0.3,
        "noise_enabled": true,
        "noise_type": "salt_pepper",
        "noise_quantity": 0.3,
        "noise_transparency": 0,
        "results_dir": "results/exp_icecream_noise_saltpepper_30",
        "log_dir": "logs/exp_icecream_noise_saltpepper_30"
    },
    {
        "file_path": "mnist_784.csv",
        "chunk_size": 70000,
        "views": "{'bottom_right', 'top_right', 'original', 'tda', 'top_left', 'bottom_left'}",
        "num_jobs": 28,
        "save_sample_views": false,
        "vary_train_split": false,
        "subsample_dataset": false,
        "exp_name": "exp_icecream_noise_saltpepper_30",
        "random_state": 142198958,
        "train_split": 0.8,
        "test_split": 0.3,
        "noise_enabled": true,
        "noise_type": "salt_pepper",
        "noise_quantity": 0.3,
        "noise_transparency": 0,
        "results_dir": "results/exp_icecream_noise_saltpepper_30",
        "log_dir": "logs/exp_icecream_noise_saltpepper_30"
    },
    {
        "file_path": "mnist_784.csv",
        "chunk_size": 70000,
        "views": "{'bottom_right', 'top_right', 'original', 'tda', 'top_left', 'bottom_left'}",
        "num_jobs": 28,
        "save_sample_views": false,
        "vary_train_split": false,
        "subsample_dataset": false,
        "exp_name": "exp_icecream_noise_saltpepper_30",
        "random_state": 532544046,
        "train_split": 0.8,
        "test_split": 0.3,
        "noise_enabled": true,
        "noise_type": "salt_pepper",
        "noise_quantity": 0.3,
        "noise_transparency": 0,
        "results_dir": "results/exp_icecream_noise_saltpepper_30",
        "log_dir": "logs/exp_icecream_noise_saltpepper_30"
    },
    {
        "file_path": "mnist_784.csv",
        "chunk_size": 70000,
        "views": "{'bottom_right', 'top_right', 'original', 'tda', 'top_left', 'bottom_left'}",
        "num_jobs": 28,
        "save_sample_views": false,
        "vary_train_split": false,
        "subsample_dataset": false,
        "exp_name": "exp_icecream_noise_saltpepper_30",
        "random_state": 528273647,
        "train_split": 0.8,
        "test_split": 0.3,
        "noise_enabled": true,
        "noise_type": "salt_pepper",
        "noise_quantity": 0.3,
        "noise_transparency": 0,
        "results_dir": "results/exp_icecream_noise_saltpepper_30",
        "log_dir": "logs/exp_icecream_noise_saltpepper_30"
    },
    {
        "file_path": "mnist_784.csv",
        "chunk_size": 70000,
        "views": "{'bottom_right', 'top_right', 'original', 'tda', 'top_left', 'bottom_left'}",
        "num_jobs": 28,
        "save_sample_views": false,
        "vary_train_split": false,
        "subsample_dataset": false,
        "exp_name": "exp_icecream_noise_saltpepper_30",
        "random_state": 459151642,
        "train_split": 0.8,
        "test_split": 0.3,
        "noise_enabled": true,
        "noise_type": "salt_pepper",
        "noise_quantity": 0.3,
        "noise_transparency": 0,
        "results_dir": "results/exp_icecream_noise_saltpepper_30",
        "log_dir": "logs/exp_icecream_noise_saltpepper_30"
    }
]